setup.py
yusprob_distribution/Binomialdistribution.py
yusprob_distribution/Gaussiandistribution.py
yusprob_distribution/Generaldistribution.py
yusprob_distribution/__init__.py
yusprob_distribution.egg-info/PKG-INFO
yusprob_distribution.egg-info/SOURCES.txt
yusprob_distribution.egg-info/dependency_links.txt
yusprob_distribution.egg-info/not-zip-safe
yusprob_distribution.egg-info/top_level.txt