Metadata-Version: 1.0
Name: yusprob-distribution
Version: 0.1
Summary: Gaussian  and Bionomial distributions
Home-page: UNKNOWN
Author: Yusuf Abubakar
Author-email: uoooosuf@gmail.com
License: UNKNOWN
Platform: UNKNOWN
